LogWeaver/__init__.py
openclone_logweaver-1.0.1.dist-info/LICENSE
openclone_logweaver-1.0.1.dist-info/METADATA
openclone_logweaver-1.0.1.dist-info/WHEEL
openclone_logweaver-1.0.1.dist-info/top_level.txt
openclone_logweaver-1.0.1.dist-info/RECORD
